src/sample_code/syncing.py
src/sdk/__init__.py
src/sdk/server.py
cord_sdk_server-0.0.1.dist-info/METADATA
cord_sdk_server-0.0.1.dist-info/WHEEL
cord_sdk_server-0.0.1.dist-info/licenses/LICENSE
cord_sdk_server-0.0.1.dist-info/RECORD
