Metadata-Version: 2.1
Name: cord-sdk_server
Version: 0.0.1
Summary: The Cord Server SDK for Python
Project-URL: Homepage, https://github.com/getcord/sdk-python
License: MIT License
License-File: LICENSE
Keywords: cord,cord-sdk,sdk,server
Classifier: License :: OSI Approved :: MIT License
Classifier: Programming Language :: Python :: 3.9
Requires-Python: >=3.9
Requires-Dist: pyjwt
